0x_contract_wrappers-1.2.0-py3.7-nspkg.pth
zero_ex/contract_wrappers/__init__.py
zero_ex/contract_wrappers/bases.py
zero_ex/contract_wrappers/py.typed
zero_ex/contract_wrappers/tx_params.py
zero_ex/contract_wrappers/asset_proxy_owner/__init__.py
zero_ex/contract_wrappers/coordinator/__init__.py
zero_ex/contract_wrappers/coordinator_registry/__init__.py
zero_ex/contract_wrappers/dev_utils/__init__.py
zero_ex/contract_wrappers/dummy_erc20_token/__init__.py
zero_ex/contract_wrappers/dummy_erc721_token/__init__.py
zero_ex/contract_wrappers/dutch_auction/__init__.py
zero_ex/contract_wrappers/erc1155_proxy/__init__.py
zero_ex/contract_wrappers/erc20_proxy/__init__.py
zero_ex/contract_wrappers/erc20_token/__init__.py
zero_ex/contract_wrappers/erc721_proxy/__init__.py
zero_ex/contract_wrappers/erc721_token/__init__.py
zero_ex/contract_wrappers/eth_balance_checker/__init__.py
zero_ex/contract_wrappers/exchange/__init__.py
zero_ex/contract_wrappers/exchange/types.py
zero_ex/contract_wrappers/exchange/validator.py
zero_ex/contract_wrappers/forwarder/__init__.py
zero_ex/contract_wrappers/i_asset_proxy/__init__.py
zero_ex/contract_wrappers/i_validator/__init__.py
zero_ex/contract_wrappers/i_wallet/__init__.py
zero_ex/contract_wrappers/multi_asset_proxy/__init__.py
zero_ex/contract_wrappers/order_validator/__init__.py
zero_ex/contract_wrappers/static_call_proxy/__init__.py
zero_ex/contract_wrappers/weth9/__init__.py
zero_ex/contract_wrappers/zrx_token/__init__.py
0x_contract_wrappers-1.2.0.dist-info/METADATA
0x_contract_wrappers-1.2.0.dist-info/WHEEL
0x_contract_wrappers-1.2.0.dist-info/namespace_packages.txt
0x_contract_wrappers-1.2.0.dist-info/top_level.txt
0x_contract_wrappers-1.2.0.dist-info/RECORD
