Metadata-Version: 2.1
Name: 0x-contract-wrappers
Version: 1.2.0
Summary: Python wrappers for 0x smart contracts
Home-page: https://github.com/0xproject/0x-monorepo/tree/development/python-packages/contract_wrappers
Author: F. Eugene Aumson
Author-email: feuGeneA@users.noreply.github.com
License: Apache 2.0
Keywords: ethereum cryptocurrency 0x decentralized blockchain dex exchange
Platform: UNKNOWN
Classifier: Development Status :: 2 - Pre-Alpha
Classifier: Intended Audience :: Developers
Classifier: Intended Audience :: Financial and Insurance Industry
Classifier: License :: OSI Approved :: Apache Software License
Classifier: Natural Language :: English
Classifier: Operating System :: OS Independent
Classifier: Programming Language :: Python
Classifier: Programming Language :: Python :: 3 :: Only
Classifier: Programming Language :: Python :: 3.6
Classifier: Programming Language :: Python :: 3.7
Classifier: Topic :: Internet :: WWW/HTTP
Classifier: Topic :: Office/Business :: Financial
Classifier: Topic :: Other/Nonlisted Topic
Classifier: Topic :: Security :: Cryptography
Classifier: Topic :: Software Development :: Libraries
Classifier: Topic :: Utilities
Requires-Python: >=3.6, <4
Requires-Dist: 0x-contract-addresses
Requires-Dist: 0x-contract-artifacts
Requires-Dist: 0x-json-schemas
Requires-Dist: 0x-order-utils
Requires-Dist: web3
Requires-Dist: attrs
Requires-Dist: eth-utils
Requires-Dist: mypy-extensions
Provides-Extra: dev
Requires-Dist: bandit ; extra == 'dev'
Requires-Dist: black ; extra == 'dev'
Requires-Dist: coverage ; extra == 'dev'
Requires-Dist: coveralls ; extra == 'dev'
Requires-Dist: mypy ; extra == 'dev'
Requires-Dist: mypy-extensions ; extra == 'dev'
Requires-Dist: pycodestyle ; extra == 'dev'
Requires-Dist: pydocstyle ; extra == 'dev'
Requires-Dist: pylint ; extra == 'dev'
Requires-Dist: pytest ; extra == 'dev'
Requires-Dist: sphinx ; extra == 'dev'
Requires-Dist: sphinx-autodoc-typehints ; extra == 'dev'
Requires-Dist: tox ; extra == 'dev'
Requires-Dist: twine ; extra == 'dev'
